server.py
ide_config_mcp-0.1.5.dist-info/METADATA
ide_config_mcp-0.1.5.dist-info/WHEEL
ide_config_mcp-0.1.5.dist-info/entry_points.txt
ide_config_mcp-0.1.5.dist-info/top_level.txt
ide_config_mcp-0.1.5.dist-info/RECORD
