Metadata-Version: 2.4
Name: ide-config-mcp
Version: 0.1.5
Summary: IDE config MCP Python package
Author-email: arcsinw <your@email.com>
Project-URL: Homepage, https://github.com/arcsinw/ide-config-mcp
Project-URL: Repository, https://github.com/arcsinw/ide-config-mcp
Requires-Python: >=3.7
Requires-Dist: fastmcp==0.6.0
Requires-Dist: commentjson==0.9.0
Requires-Dist: fastapi==0.103.1
Requires-Dist: uvicorn==0.23.2
